{
  "id": "talon_06",
  "name": {
    "fr": "Taverne des Vagues Brillantes",
    "en": "Shining Waves Tavern"
  },
  "description": {
    "fr": "Une ambiance chaleureuse et accueillante enveloppe cette taverne en bois, où les murs sont ornés de filets de pêche colorés et d'ancres rouillées. Le crépitement du feu et les rires des marins se mêlent aux chansons folkloriques qui racontent les exploits de corsaires et les légendes marines. Ici, les joueurs peuvent écouter des rumeurs, recruter des compagnons de voyage ou simplement se reposer après une journée d'aventures.",
    "en": "A warm and welcoming atmosphere envelops this wooden tavern, where the walls are adorned with colorful fishing nets and rusty anchors. The crackling of the fire and the laughter of the sailors mingle with the folk songs that tell the exploits of corsairs and sea legends. Here, players can listen to rumors, recruit travel companions or simply rest after a day of adventures."
  },
  "region": "oraland",
  "town": {
    "isTownPlace": true,
    "id": "talon",
    "isEntryPoint": false
  },
  "availableMoves": [
    {
      "id": "talon_02",
      "town": "talon",
      "region": "oraland",
      "duration": 1
    }
  ]
}